spark_etl_python/__init__.py
spark_etl_python/deduplication.py
spark_etl_python/derivations.py
spark_etl_python-0.1.5.dist-info/AUTHORS.rst
spark_etl_python-0.1.5.dist-info/LICENSE
spark_etl_python-0.1.5.dist-info/METADATA
spark_etl_python-0.1.5.dist-info/WHEEL
spark_etl_python-0.1.5.dist-info/top_level.txt
spark_etl_python-0.1.5.dist-info/RECORD
