Metadata-Version: 2.1
Name: spark-etl-python
Version: 0.1.5
Summary: A Python package that provides helpers for cleaning, deduplication, enrichment, etc. in Spark
Home-page: https://github.com/flavianh/spark_etl_python
Author: Flavian Hautbois
Author-email: flavianh@sicara.com
License: MIT license
Keywords: spark_etl_python
Platform: UNKNOWN
Classifier: Development Status :: 2 - Pre-Alpha
Classifier: Intended Audience :: Developers
Classifier: License :: OSI Approved :: MIT License
Classifier: Natural Language :: English
Classifier: Programming Language :: Python :: 2
Classifier: Programming Language :: Python :: 2.7
Classifier: Programming Language :: Python :: 3
Classifier: Programming Language :: Python :: 3.4
Classifier: Programming Language :: Python :: 3.5
Classifier: Programming Language :: Python :: 3.6
Classifier: Programming Language :: Python :: 3.7
